{
  "id": 12,
  "title": "Networking Essentials",
  "subtitle": "OSI model, WebSockets, load balancers, and how data moves across networks",
  "group": "scale",
  "sections": [
    {
      "title": "The OSI Model",
      "text": "<p>The OSI model describes how data travels across a network in 7 layers. You only need to care about a few:</p><ul><li><strong>Layer 7 (Application)</strong> — Where your code lives. HTTP, DNS, SMTP.</li><li><strong>Layer 4 (Transport)</strong> — TCP (guaranteed delivery) and UDP (fast, no guarantee). Ports live here.</li><li><strong>Layer 3 (Network)</strong> — IP routing. Getting data from your computer to a server across the world.</li><li><strong>Layers 1-2</strong> — Physical cables and Wi-Fi. Rarely your problem.</li></ul><p>The internet actually uses TCP/IP (a simpler 4-layer model), but OSI helps you debug: \"Can't reach the website? Is it Layer 7 (server crashed?), Layer 4 (port blocked?), or Layer 3 (IP unreachable?)</p>",
      "diagram": {
        "type": "annotation",
        "config": {
          "elements": [
            { "x": 180, "y": 10, "w": 140, "h": 30, "label": "7. Application", "color": "#00E5FF" },
            { "x": 180, "y": 44, "w": 140, "h": 30, "label": "6. Presentation", "color": "#8B5CF6" },
            { "x": 180, "y": 78, "w": 140, "h": 30, "label": "5. Session", "color": "#FF3D8A" },
            { "x": 180, "y": 112, "w": 140, "h": 30, "label": "4. Transport", "color": "#FFB300" },
            { "x": 180, "y": 146, "w": 140, "h": 30, "label": "3. Network", "color": "#00F593" },
            { "x": 180, "y": 180, "w": 140, "h": 30, "label": "2. Data Link", "color": "#FF3D8A" },
            { "x": 180, "y": 214, "w": 140, "h": 30, "label": "1. Physical", "color": "#8B5CF6" }
          ],
          "annotations": [
            { "target": 0, "text": "HTTP, DNS, SMTP" },
            { "target": 1, "text": "Encryption, encoding" },
            { "target": 2, "text": "TLS, session management" },
            { "target": 3, "text": "TCP, UDP, ports" },
            { "target": 4, "text": "IP routing" },
            { "target": 5, "text": "Ethernet, MAC" },
            { "target": 6, "text": "Cables, radio signals" }
          ]
        }
      },
      "caption": "The 7-layer OSI model — data moves from application to physical and back",
      "detail": "The OSI model is a teaching tool, not a strict implementation guide. The Internet uses TCP/IP (a 4-layer model: Link → Internet → Transport → Application). But understanding OSI helps diagnose network issues. If you can't reach a website: layer 7 (is the server running?), layer 4 (is the port open?), layer 3 (is the IP reachable?), layer 1 (is the cable plugged in?).",
      "code": "# Diagnose network issues by OSI layer\n\n# Layer 3 - is the host reachable?\n$ ping google.com\n\n# Layer 4 - is the port open?\n$ nc -zv google.com 80\n\n# Layer 7 - is the web server responding?\n$ curl -I https://google.com",
      "codeLang": "bash"
    },
    {
      "title": "HTTP vs WebSockets",
      "text": "<p><strong>HTTP</strong> is like sending a letter — you write, they respond, conversation over. The client asks, the server answers. Great for APIs and web pages where the client controls when data is requested.</p><p><strong>WebSockets</strong> is like a phone call — the line stays open. Both sides can talk at any time. The server can push messages to the client without waiting for a request. This is what makes live chat, real-time notifications, collaborative editing, and gaming possible.</p><p>The WebSocket connection starts as HTTP (an <code>Upgrade: websocket</code> header), then switches protocols. This lets it work through standard firewalls and proxies.</p>",
      "diagram": {
        "type": "comparison",
        "config": {
          "left": {
            "header": "HTTP",
            "items": [
              "Request-response pattern",
              "Client initiates every exchange",
              "Connection closes after response",
              "Stateless — no persistent connection",
              "Higher overhead per request (headers)",
              "Best for: REST APIs, web pages"
            ]
          },
          "right": {
            "header": "WebSocket",
            "items": [
              "Full-duplex — both sides can send",
              "Server can push data to client",
              "Persistent connection stays open",
              "Stateful connection maintained",
              "Low overhead per message (frames)",
              "Best for: chat, gaming, live data"
            ]
          },
          "vsLabel": "VS"
        }
      },
      "caption": "HTTP for request-response, WebSockets for real-time bidirectional communication",
      "code": "// WebSocket server (Node.js + ws)\nconst WebSocket = require('ws');\nconst wss = new WebSocket.Server({ port: 8080 });\n\nwss.on('connection', (ws) => {\n  ws.on('message', (data) => {\n    // Broadcast to all connected clients\n    wss.clients.forEach(client => {\n      if (client.readyState === WebSocket.OPEN) {\n        client.send(data);\n      }\n    });\n  });\n});\n\n// WebSocket client (browser)\nconst ws = new WebSocket('ws://localhost:8080');\nws.onmessage = (event) => {\n  console.log('Received:', event.data);\n};\nws.send('Hello server!');",
      "codeLang": "javascript"
    },
    {
      "title": "Load Balancers",
      "text": "<p>A <strong>load balancer</strong> sits in front of your servers and distributes traffic. It's like having a host at a restaurant who decides which waiter takes your order. If one server goes down, the load balancer stops sending traffic to it — your users never notice.</p><p>Common strategies:</p><ul><li><strong>Round Robin</strong> — Take turns. Simple, but ignores actual server load.</li><li><strong>Least Connections</strong> — Send to the least busy server. Smarter.</li><li><strong>IP Hash</strong> — Same user always goes to the same server (for sticky sessions).</li></ul><p>Load balancers also handle SSL termination (decrypting HTTPS before it reaches your servers) and health checks (pinging servers to make sure they're alive).</p>",
      "diagram": {
        "type": "stepFlow",
        "config": {
          "steps": [
            { "label": "Client Request", "desc": "User hits example.com", "color": "#00E5FF" },
            { "label": "Load Balancer", "desc": "Routes to healthy server", "color": "#8B5CF6" },
            { "label": "Server A", "desc": "Handles request", "color": "#00F593" },
            { "label": "Server B", "desc": "Idle / handling other request", "color": "#FFB300" },
            { "label": "Server C", "desc": "Health check failed (removed)", "color": "#FF3D8A" }
          ]
        }
      },
      "caption": "Load balancer distributes traffic across healthy servers, routing around failures",
      "code": "# Nginx load balancing config\nupstream backend {\n  least_conn;  # least connections algorithm\n  server app1.example.com weight=3;\n  server app2.example.com weight=2;\n  server app3.example.com;  # weight=1 default\n}\n\nserver {\n  listen 80;\n  location / {\n    proxy_pass http://backend;\n    proxy_set_header Host $host;\n  }\n}",
      "codeLang": "nginx",
      "callout": "Load balancers are the first line of defense for scaling. They handle SSL termination, health checks, and can prevent the thundering herd problem during server restarts.",
      "calloutType": "info",
      "calloutTitle": "Scaling 101"
    }
  ]
}
